lumod/__init__.py
lumod/data/attributes.csv
lumod/data/example1.csv
lumod/data/example2.csv
lumod/data/example3.csv
lumod/fluxes/__init__.py
lumod/fluxes/abstractions.py
lumod/fluxes/baseflow.py
lumod/fluxes/evapotranpiration.py
lumod/fluxes/groundwater.py
lumod/fluxes/infiltration.py
lumod/fluxes/interception.py
lumod/fluxes/percolation.py
lumod/fluxes/pet_models.py
lumod/fluxes/recharge.py
lumod/fluxes/routine.py
lumod/fluxes/snow.py
lumod/models/__init__.py
lumod/models/base_model.py
lumod/models/gr1a_model.py
lumod/models/gr2m_model.py
lumod/models/gr4j_model.py
lumod/models/hbv_model.py
lumod/models/hymod_model.py
lumod/models/milc_iuh.txt
lumod/models/milc_model.py
lumod/tools/__init__.py
lumod/tools/metrics.py
lumod/tools/monte_carlo.py
lumod/tools/plots.py
lumod/tools/time_series.py
lumod-0.1.3.0.dist-info/LICENSE.md
lumod-0.1.3.0.dist-info/WHEEL
lumod-0.1.3.0.dist-info/METADATA
lumod-0.1.3.0.dist-info/RECORD
