Metadata-Version: 2.1
Name: lumod
Version: 0.1.3.0
Summary: Hydrological Lumped Model Tools
Home-page: https://gitlab.com/Zaul_AE/lumod
License: GNU-3
Author: Saul Arciniega Esparza
Author-email: zaul_ae@hotmail.com
Requires-Python: >=3.7,<4.0
Classifier: License :: Other/Proprietary License
Classifier: Programming Language :: Python :: 3
Classifier: Programming Language :: Python :: 3.10
Classifier: Programming Language :: Python :: 3.7
Classifier: Programming Language :: Python :: 3.8
Classifier: Programming Language :: Python :: 3.9
Requires-Dist: matplotlib
Requires-Dist: numba
Requires-Dist: numpy
Requires-Dist: pandas
Project-URL: Documentation, https://zaul_ae.gitlab.io/lumod-docs
Project-URL: Repository, https://gitlab.com/Zaul_AE/lumod
